LICENSE.txt
MANIFEST.in
README.md
setup.py
jk_asyncio_logging/AsyncioBufferLogger.py
jk_asyncio_logging/AsyncioConsoleLogger.py
jk_asyncio_logging/AsyncioFileLogger.py
jk_asyncio_logging/AsyncioFilterLogger.py
jk_asyncio_logging/AsyncioLogWrapper.py
jk_asyncio_logging/AsyncioMulticastLogger.py
jk_asyncio_logging/AsyncioNamedMulticastLogger.py
jk_asyncio_logging/AsyncioNullLogger.py
jk_asyncio_logging/AsyncioStringListLogger.py
jk_asyncio_logging/__init__.py
jk_asyncio_logging/_inst.py
jk_asyncio_logging.egg-info/PKG-INFO
jk_asyncio_logging.egg-info/SOURCES.txt
jk_asyncio_logging.egg-info/dependency_links.txt
jk_asyncio_logging.egg-info/not-zip-safe
jk_asyncio_logging.egg-info/requires.txt
jk_asyncio_logging.egg-info/top_level.txt