Metadata-Version: 2.1
Name: jk-asyncio-logging
Version: 0.2019.10.19
Summary: This is a logging framework. It is based on jk_logging but can be used with Asyncio.
Home-page: https://github.com/jkpubsrc/python-module-jk-asyncio-logging
Author: Jürgen Knauth
Author-email: pubsrc@binary-overflow.de
License: Apache 2.0
Download-URL: https://github.com/jkpubsrc/python-module-jk-asyncio-logging/tarball/0.2019.10.19
Keywords: debugging,logging,asyncio
Platform: UNKNOWN
Classifier: Development Status :: 5 - Production/Stable
Classifier: License :: OSI Approved :: Apache Software License
Classifier: Topic :: Software Development :: Testing
Classifier: Topic :: System :: Logging
